lily/__init__.py
lily/lily.py
lily_thing-0.0.1.dist-info/LICENSE
lily_thing-0.0.1.dist-info/METADATA
lily_thing-0.0.1.dist-info/WHEEL
lily_thing-0.0.1.dist-info/top_level.txt
lily_thing-0.0.1.dist-info/RECORD
