Metadata-Version: 2.1
Name: lily-thing
Version: 0.0.1
Summary: Does the thing that Lily needs
Home-page: UNKNOWN
Author: Luke Burns
Author-email: lukemburns@gmail.com
License: UNKNOWN
Platform: UNKNOWN
Classifier: Programming Language :: Python :: 3
Classifier: License :: OSI Approved :: MIT License
Classifier: Operating System :: OS Independent
Requires-Python: >=3.6
